dna_hash/__init__.py
dna_hash/dna_hash.py
dna_hash/py.typed
dna_hash/tokenizers.py
dnahash-0.0.3.dist-info/licenses/LICENSE
dnahash-0.0.3.dist-info/METADATA
dnahash-0.0.3.dist-info/WHEEL
dnahash-0.0.3.dist-info/top_level.txt
dnahash-0.0.3.dist-info/RECORD
