Metadata-Version: 2.4
Name: DNAHash
Version: 0.0.3
Summary: A specialized datastructure and tokenization library for counting genetic sequences for use in Machine Learning and Bioinformatics.
Author-email: Andrew DalPino <support@andrewdalpino.com>
License: MIT
Project-URL: Homepage, https://github.com/andrewdalpino/DNAHash
Project-URL: Documentation, https://github.com/andrewdalpino/DNAHash/README.md
Project-URL: Source, https://github.com/andrewdalpino/DNAHash
Requires-Python: >=3.10
License-File: LICENSE
Requires-Dist: okbloomer>=0.0.3
Provides-Extra: dev
Requires-Dist: mypy; extra == "dev"
Requires-Dist: black; extra == "dev"
Requires-Dist: biopython; extra == "dev"
Requires-Dist: matplotlib; extra == "dev"
Provides-Extra: test
Requires-Dist: mypy; extra == "test"
Requires-Dist: black; extra == "test"
Dynamic: license-file
